ksrpy/__init__.py
ksrpy/main.py
ksrpy/utils/__init__.py
ksrpy/utils/date_utils.py
ksrpy/utils/math_utils.py
ksrpy/utils/string_utils.py
ksrpy-0.1.0.dist-info/METADATA
ksrpy-0.1.0.dist-info/WHEEL
ksrpy-0.1.0.dist-info/top_level.txt
ksrpy-0.1.0.dist-info/RECORD
